{
  "bids_meta": {
    "EchoTime": 0.037,
    "FlipAngle": 8,
    "ParallelAcquisitionTechnique": "SENSE",
    "ParallelReductionFactorInPlan": [
      1,
      1.5
    ],
    "PhaseEncodingDirection": [
      "i-",
      "j-"
    ],
    "PulseSequenceType": "3D fast-field echo",
    "RepetitionTime": 0.081,
    "WaterFatShift": 2.268,
    "dataset": "ds003097",
    "modality": "T1w",
    "run_id": 2,
    "subject_id": "0231"
  },
  "cjv": 0.4707598069711925,
  "cnr": 2.6439201101846814,
  "efc": 0.7323946646747197,
  "fber": 29864.029296875,
  "fwhm_avg": 4.23603,
  "fwhm_x": 4.07706,
  "fwhm_y": 4.55886,
  "fwhm_z": 4.07217,
  "icvs_csf": 0.1968424801644093,
  "icvs_gm": 0.4388593417822882,
  "icvs_wm": 0.3642981780533025,
  "inu_med": 1.0109763145446777,
  "inu_range": 0.37759449183940874,
  "provenance": {
    "md5sum": "1e9ff30744651a4e517f0825ab72dee2",
    "settings": {
      "testing": false
    },
    "software": "mriqc",
    "version": "21.0.0rc2",
    "warnings": {
      "large_rot_frame": true,
      "small_air_mask": false
    },
    "webapi_port": null,
    "webapi_url": "https://mriqc.nimh.nih.gov/api/v1"
  },
  "qi_1": 0.003995656947250308,
  "qi_2": 0.0218699228668598,
  "rpve_csf": 21.68459316572644,
  "rpve_gm": 10.523661941052188,
  "rpve_wm": 14.508769113064456,
  "size_x": 160,
  "size_y": 256,
  "size_z": 256,
  "snr_csf": 2.5965779850901236,
  "snr_gm": 10.924276080653396,
  "snr_total": 13.508769964621456,
  "snr_wm": 27.00545582812084,
  "snrd_csf": 42.92987501478444,
  "snrd_gm": 88.69430688205465,
  "snrd_total": 81.54968972550002,
  "snrd_wm": 113.02488727966094,
  "spacing_x": 1.0,
  "spacing_y": 1.0,
  "spacing_z": 1.0,
  "summary_bg_k": 1289.6272910827468,
  "summary_bg_mad": 5.79644458173821,
  "summary_bg_mean": 4.939009189605713,
  "summary_bg_median": 3.909642457962036,
  "summary_bg_n": 459844.0,
  "summary_bg_p05": 0.0,
  "summary_bg_p95": 15.661371946334837,
  "summary_bg_stdv": 9.90099811553955,
  "summary_csf_k": 27.244451744289577,
  "summary_csf_mad": 88.52829233341384,
  "summary_csf_mean": 422.002685546875,
  "summary_csf_median": 379.8302917480469,
  "summary_csf_n": 35941.0,
  "summary_csf_p05": 287.5672607421875,
  "summary_csf_p95": 645.212890625,
  "summary_csf_stdv": 146.27906799316406,
  "summary_gm_k": 0.1651634278021623,
  "summary_gm_mad": 69.46060166750873,
  "summary_gm_mean": 793.12451171875,
  "summary_gm_median": 784.7398681640625,
  "summary_gm_n": 41632.0,
  "summary_gm_p05": 689.5803070068359,
  "summary_gm_p95": 925.7598510742188,
  "summary_gm_stdv": 71.83363342285156,
  "summary_wm_k": 1.3454810197042315,
  "summary_wm_mad": 31.879612577621998,
  "summary_wm_mean": 999.0779418945312,
  "summary_wm_median": 1000.0093383789062,
  "summary_wm_n": 240290.0,
  "summary_wm_p05": 934.8824066162109,
  "summary_wm_p95": 1056.8281372070312,
  "summary_wm_stdv": 37.029823303222656,
  "tpm_overlap_csf": 0.16953474283218384,
  "tpm_overlap_gm": 0.46499764919281006,
  "tpm_overlap_wm": 0.4987252354621887,
  "wm2max": 0.6391805464699577
}