{
  "bids_meta": {
    "EchoTime": 0.037,
    "FlipAngle": 8,
    "ParallelAcquisitionTechnique": "SENSE",
    "ParallelReductionFactorInPlan": [
      1,
      1.5
    ],
    "PhaseEncodingDirection": [
      "i-",
      "j-"
    ],
    "PulseSequenceType": "3D fast-field echo",
    "RepetitionTime": 0.081,
    "WaterFatShift": 2.268,
    "dataset": "ds003097",
    "modality": "T1w",
    "run_id": 2,
    "subject_id": "0115"
  },
  "cjv": 0.4887798746348449,
  "cnr": 2.4583208469346176,
  "efc": 0.7315725442639368,
  "fber": 33929.390625,
  "fwhm_avg": 4.35787,
  "fwhm_x": 4.16751,
  "fwhm_y": 4.76018,
  "fwhm_z": 4.14592,
  "icvs_csf": 0.21740064538590742,
  "icvs_gm": 0.418112972358653,
  "icvs_wm": 0.36448638225543956,
  "inu_med": 1.0567288398742676,
  "inu_range": 0.40565086007118223,
  "provenance": {
    "md5sum": "3e19b85f4c8d60b83426a674d22b9698",
    "settings": {
      "testing": false
    },
    "software": "mriqc",
    "version": "21.0.0rc2",
    "warnings": {
      "large_rot_frame": true,
      "small_air_mask": false
    },
    "webapi_port": null,
    "webapi_url": "https://mriqc.nimh.nih.gov/api/v1"
  },
  "qi_1": 0.002020042232516123,
  "qi_2": 0.006985898499982377,
  "rpve_csf": 19.714088458044166,
  "rpve_gm": 10.58753575021761,
  "rpve_wm": 14.14943649333691,
  "size_x": 160,
  "size_y": 256,
  "size_z": 256,
  "snr_csf": 3.632761559292809,
  "snr_gm": 10.611357889336285,
  "snr_total": 13.704868359686905,
  "snr_wm": 26.87048563043162,
  "snrd_csf": 43.5553041859235,
  "snrd_gm": 96.1485443144385,
  "snrd_total": 86.92500351187476,
  "snrd_wm": 121.07116203526232,
  "spacing_x": 1.0,
  "spacing_y": 1.0,
  "spacing_z": 1.0,
  "summary_bg_k": 9.179998993576119,
  "summary_bg_mad": 5.411229594202538,
  "summary_bg_mean": 4.732812881469727,
  "summary_bg_median": 3.6498188972473145,
  "summary_bg_n": 568618.0,
  "summary_bg_p05": 0.0,
  "summary_bg_p95": 14.716780424118042,
  "summary_bg_stdv": 5.100001811981201,
  "summary_csf_k": 17.686663365936454,
  "summary_csf_mad": 54.941479227573666,
  "summary_csf_mean": 391.76220703125,
  "summary_csf_median": 359.75372314453125,
  "summary_csf_n": 48174.0,
  "summary_csf_p05": 293.9446319580078,
  "summary_csf_p95": 603.826025390625,
  "summary_csf_stdv": 99.02934265136719,
  "summary_gm_k": 0.5696791104188033,
  "summary_gm_mad": 67.3446539334196,
  "summary_gm_mean": 802.862060546875,
  "summary_gm_median": 794.1580810546875,
  "summary_gm_n": 33233.0,
  "summary_gm_p05": 696.4262329101563,
  "summary_gm_p95": 946.8164672851562,
  "summary_gm_stdv": 74.8392562866211,
  "summary_wm_k": 0.9805227378633123,
  "summary_wm_mad": 33.27231212864192,
  "summary_wm_mean": 998.4657592773438,
  "summary_wm_median": 1000.0114135742188,
  "summary_wm_n": 250808.0,
  "summary_wm_p05": 934.0590759277344,
  "summary_wm_p95": 1055.967529296875,
  "summary_wm_stdv": 37.215904235839844,
  "tpm_overlap_csf": 0.18807458877563477,
  "tpm_overlap_gm": 0.4660790264606476,
  "tpm_overlap_wm": 0.5112637281417847,
  "wm2max": 0.6187128727896019
}