{
  "bids_meta": {
    "EchoTime": 0.037,
    "FlipAngle": 8,
    "ParallelAcquisitionTechnique": "SENSE",
    "ParallelReductionFactorInPlan": [
      1,
      1.5
    ],
    "PhaseEncodingDirection": [
      "i-",
      "j-"
    ],
    "PulseSequenceType": "3D fast-field echo",
    "RepetitionTime": 0.081,
    "WaterFatShift": 2.268,
    "dataset": "ds003097",
    "modality": "T1w",
    "run_id": 2,
    "subject_id": "0008"
  },
  "cjv": 0.47378226036136706,
  "cnr": 2.677830492854449,
  "efc": 0.6461141059916055,
  "fber": 35649.68359375,
  "fwhm_avg": 4.2524033333333335,
  "fwhm_x": 4.04974,
  "fwhm_y": 4.66815,
  "fwhm_z": 4.03932,
  "icvs_csf": 0.20318437140154563,
  "icvs_gm": 0.4179502323372918,
  "icvs_wm": 0.37886539626116256,
  "inu_med": 0.7548457980155945,
  "inu_range": 0.2527377367019653,
  "provenance": {
    "md5sum": "2418eafbbd1b5ae35768959aaedbe36e",
    "settings": {
      "testing": false
    },
    "software": "mriqc",
    "version": "21.0.0rc2",
    "warnings": {
      "large_rot_frame": true,
      "small_air_mask": false
    },
    "webapi_port": null,
    "webapi_url": "https://mriqc.nimh.nih.gov/api/v1"
  },
  "qi_1": 0.009168258532570592,
  "qi_2": 0.003897009201781188,
  "rpve_csf": 24.014153066382313,
  "rpve_gm": 12.329066340591998,
  "rpve_wm": 16.109066136112038,
  "size_x": 160,
  "size_y": 256,
  "size_z": 256,
  "snr_csf": 3.290554064304434,
  "snr_gm": 11.87937662838397,
  "snr_total": 14.834060724544893,
  "snr_wm": 29.332251480946276,
  "snrd_csf": 41.84940899248667,
  "snrd_gm": 94.59588289846405,
  "snrd_total": 85.02769189971018,
  "snrd_wm": 118.63778380817983,
  "spacing_x": 1.0,
  "spacing_y": 1.0,
  "spacing_z": 1.0,
  "summary_bg_k": 114.6428221774361,
  "summary_bg_mad": 5.522200725020769,
  "summary_bg_mean": 5.266523361206055,
  "summary_bg_median": 3.72466778755188,
  "summary_bg_n": 949091.0,
  "summary_bg_p05": 0.0,
  "summary_bg_p95": 15.043751239776611,
  "summary_bg_stdv": 7.7254414558410645,
  "summary_csf_k": 57.17256566699536,
  "summary_csf_mad": 49.60864935748536,
  "summary_csf_mean": 386.1734619140625,
  "summary_csf_median": 352.75225830078125,
  "summary_csf_n": 34256.0,
  "summary_csf_p05": 293.78487396240234,
  "summary_csf_p95": 591.0632629394531,
  "summary_csf_stdv": 107.19991302490234,
  "summary_gm_k": 0.12272047364237526,
  "summary_gm_mad": 64.79127339145349,
  "summary_gm_mean": 801.9669189453125,
  "summary_gm_median": 797.3568115234375,
  "summary_gm_n": 31054.0,
  "summary_gm_p05": 699.7943817138672,
  "summary_gm_p95": 920.9576354980468,
  "summary_gm_stdv": 67.1200180053711,
  "summary_wm_k": 0.9727893185901966,
  "summary_wm_mad": 31.221291585213045,
  "summary_wm_mean": 998.4557495117188,
  "summary_wm_median": 1000.008056640625,
  "summary_wm_n": 224710.0,
  "summary_wm_p05": 939.5374755859375,
  "summary_wm_p95": 1050.73134765625,
  "summary_wm_stdv": 34.09236526489258,
  "tpm_overlap_csf": 0.16086271405220032,
  "tpm_overlap_gm": 0.43886545300483704,
  "tpm_overlap_wm": 0.483860582113266,
  "wm2max": 0.6881473063405568
}