{
  "bids_meta": {
    "EchoTime": 0.037,
    "FlipAngle": 8,
    "ParallelAcquisitionTechnique": "SENSE",
    "ParallelReductionFactorInPlan": [
      1,
      1.5
    ],
    "PhaseEncodingDirection": [
      "i-",
      "j-"
    ],
    "PulseSequenceType": "3D fast-field echo",
    "RepetitionTime": 0.081,
    "WaterFatShift": 2.268,
    "dataset": "ds003097",
    "modality": "T1w",
    "run_id": 3,
    "subject_id": "0044"
  },
  "cjv": 0.442779798187422,
  "cnr": 2.8524156815996973,
  "efc": 0.615744426099001,
  "fber": 24008.580078125,
  "fwhm_avg": 4.146776666666667,
  "fwhm_x": 3.98161,
  "fwhm_y": 4.42844,
  "fwhm_z": 4.03028,
  "icvs_csf": 0.20755670803407333,
  "icvs_gm": 0.4295632687636843,
  "icvs_wm": 0.3628800232022424,
  "inu_med": 0.7395879626274109,
  "inu_range": 0.27599077820777895,
  "provenance": {
    "md5sum": "675d8ebc96df1fdfe6c562d8841c4cca",
    "settings": {
      "testing": false
    },
    "software": "mriqc",
    "version": "21.0.0rc2",
    "warnings": {
      "large_rot_frame": true,
      "small_air_mask": false
    },
    "webapi_port": null,
    "webapi_url": "https://mriqc.nimh.nih.gov/api/v1"
  },
  "qi_1": 0.015089482777979812,
  "qi_2": 0.003255286246080472,
  "rpve_csf": 23.06275650325884,
  "rpve_gm": 11.898447394830033,
  "rpve_wm": 16.625809823029496,
  "size_x": 160,
  "size_y": 256,
  "size_z": 256,
  "snr_csf": 3.507745640845075,
  "snr_gm": 10.726681023103083,
  "snr_total": 13.3637029480496,
  "snr_wm": 25.85668218020064,
  "snrd_csf": 46.382064684897,
  "snrd_gm": 77.9089948858599,
  "snrd_total": 75.40006045645747,
  "snrd_wm": 101.90912179861549,
  "spacing_x": 1.0,
  "spacing_y": 1.0,
  "spacing_z": 1.0,
  "summary_bg_k": 190.75713213032864,
  "summary_bg_mad": 6.428734959777537,
  "summary_bg_mean": 6.8080949783325195,
  "summary_bg_median": 4.336115837097168,
  "summary_bg_n": 989697.0,
  "summary_bg_p05": 0.0,
  "summary_bg_p95": 21.451668548583985,
  "summary_bg_stdv": 15.548667907714844,
  "summary_csf_k": 11.51286368988291,
  "summary_csf_mad": 157.55983159741646,
  "summary_csf_mean": 451.0216064453125,
  "summary_csf_median": 455.1388244628906,
  "summary_csf_n": 20647.0,
  "summary_csf_p05": 276.1075500488281,
  "summary_csf_p95": 633.7093627929688,
  "summary_csf_stdv": 129.74937438964844,
  "summary_gm_k": 0.16978316120750625,
  "summary_gm_mad": 69.8555942629541,
  "summary_gm_mean": 769.6983032226562,
  "summary_gm_median": 764.5068969726562,
  "summary_gm_n": 21918.0,
  "summary_gm_p05": 661.4026428222656,
  "summary_gm_p95": 895.589401245117,
  "summary_gm_stdv": 71.2698974609375,
  "summary_wm_k": 1.020848414209996,
  "summary_wm_mad": 34.42299387977212,
  "summary_wm_mean": 998.3953857421875,
  "summary_wm_median": 1000.0158081054688,
  "summary_wm_n": 205724.0,
  "summary_wm_p05": 931.0865203857422,
  "summary_wm_p95": 1058.1629272460937,
  "summary_wm_stdv": 38.67523956298828,
  "tpm_overlap_csf": 0.1642257422208786,
  "tpm_overlap_gm": 0.46158367395401,
  "tpm_overlap_wm": 0.4957049489021301,
  "wm2max": 0.6876075663069295
}