{
  "bids_meta": {
    "EchoTime": 0.037,
    "FlipAngle": 8,
    "ParallelAcquisitionTechnique": "SENSE",
    "ParallelReductionFactorInPlan": [
      1,
      1.5
    ],
    "PhaseEncodingDirection": [
      "i-",
      "j-"
    ],
    "PulseSequenceType": "3D fast-field echo",
    "RepetitionTime": 0.081,
    "WaterFatShift": 2.268,
    "dataset": "ds003097",
    "modality": "T1w",
    "run_id": 1,
    "subject_id": "0754"
  },
  "cjv": 0.39920298100408647,
  "cnr": 3.0781139739315515,
  "efc": 0.7761791420903987,
  "fber": 17647.296875,
  "fwhm_avg": 4.369826666666667,
  "fwhm_x": 4.28149,
  "fwhm_y": 4.6925,
  "fwhm_z": 4.13549,
  "icvs_csf": 0.19135848633357513,
  "icvs_gm": 0.432728566571212,
  "icvs_wm": 0.37591294709521283,
  "inu_med": 1.1283109188079834,
  "inu_range": 0.4123845040798185,
  "provenance": {
    "md5sum": "29d5fc57fd34ffe332fff3d03b31b74f",
    "settings": {
      "testing": false
    },
    "software": "mriqc",
    "version": "21.0.0rc2",
    "warnings": {
      "large_rot_frame": true,
      "small_air_mask": false
    },
    "webapi_port": null,
    "webapi_url": "https://mriqc.nimh.nih.gov/api/v1"
  },
  "qi_1": 0.0002974575108987273,
  "qi_2": 0.021977779573662943,
  "rpve_csf": 21.470280298147323,
  "rpve_gm": 10.313120753791235,
  "rpve_wm": 13.799083374171126,
  "size_x": 160,
  "size_y": 256,
  "size_z": 256,
  "snr_csf": 2.2441968790902105,
  "snr_gm": 11.345312386045418,
  "snr_total": 13.831997044230079,
  "snr_wm": 27.90648186755461,
  "snrd_csf": 30.944985907850317,
  "snrd_gm": 67.10185474865142,
  "snrd_total": 61.94695061510922,
  "snrd_wm": 87.79401118882593,
  "spacing_x": 1.0,
  "spacing_y": 1.0,
  "spacing_z": 1.0,
  "summary_bg_k": 3.65457122666049,
  "summary_bg_mad": 7.462217617479299,
  "summary_bg_mean": 6.360684394836426,
  "summary_bg_median": 5.033189296722412,
  "summary_bg_n": 300916.0,
  "summary_bg_p05": 0.0,
  "summary_bg_p95": 20.18308162689209,
  "summary_bg_stdv": 6.364459037780762,
  "summary_csf_k": 66.90205944546824,
  "summary_csf_mad": 53.10689019391718,
  "summary_csf_mean": 393.9194030761719,
  "summary_csf_median": 352.4735107421875,
  "summary_csf_n": 41616.0,
  "summary_csf_p05": 290.2051086425781,
  "summary_csf_p95": 600.8242492675781,
  "summary_csf_stdv": 157.05809020996094,
  "summary_gm_k": 0.6508302521996479,
  "summary_gm_mad": 61.27416521111552,
  "summary_gm_mean": 773.0828857421875,
  "summary_gm_median": 764.3120727539062,
  "summary_gm_n": 39835.0,
  "summary_gm_p05": 677.3144287109375,
  "summary_gm_p95": 899.7802734374999,
  "summary_gm_stdv": 67.36724853515625,
  "summary_wm_k": 0.8360796541488558,
  "summary_wm_mad": 32.814156914268516,
  "summary_wm_mean": 998.099853515625,
  "summary_wm_median": 1000.0025024414062,
  "summary_wm_n": 255001.0,
  "summary_wm_p05": 935.4525756835938,
  "summary_wm_p95": 1052.6954345703125,
  "summary_wm_stdv": 35.833988189697266,
  "tpm_overlap_csf": 0.1678498536348343,
  "tpm_overlap_gm": 0.4620679020881653,
  "tpm_overlap_wm": 0.4996834993362427,
  "wm2max": 0.6529989280130732
}