{
  "bids_meta": {
    "EchoTime": 0.037,
    "FlipAngle": 8,
    "ParallelAcquisitionTechnique": "SENSE",
    "ParallelReductionFactorInPlan": [
      1,
      1.5
    ],
    "PhaseEncodingDirection": [
      "i-",
      "j-"
    ],
    "PulseSequenceType": "3D fast-field echo",
    "RepetitionTime": 0.081,
    "WaterFatShift": 2.268,
    "dataset": "ds003097",
    "modality": "T1w",
    "run_id": 2,
    "subject_id": "0851"
  },
  "cjv": 0.403552189129559,
  "cnr": 3.1713109407933118,
  "efc": 0.6890382562438023,
  "fber": 31141.478515625,
  "fwhm_avg": 4.431536666666667,
  "fwhm_x": 4.33457,
  "fwhm_y": 4.69007,
  "fwhm_z": 4.26997,
  "icvs_csf": 0.2041865779585528,
  "icvs_gm": 0.4278377846146383,
  "icvs_wm": 0.36797563742680894,
  "inu_med": 1.0085704326629639,
  "inu_range": 0.4150542259216309,
  "provenance": {
    "md5sum": "33948d1f1d476d565bc4fae4f8be0192",
    "settings": {
      "testing": false
    },
    "software": "mriqc",
    "version": "21.0.0rc2",
    "warnings": {
      "large_rot_frame": true,
      "small_air_mask": false
    },
    "webapi_port": null,
    "webapi_url": "https://mriqc.nimh.nih.gov/api/v1"
  },
  "qi_1": 0.00620146223179272,
  "qi_2": 0.0447041551914453,
  "rpve_csf": 20.939773100721585,
  "rpve_gm": 10.728364856092206,
  "rpve_wm": 14.737672983705753,
  "size_x": 160,
  "size_y": 256,
  "size_z": 256,
  "snr_csf": 3.3003101312100513,
  "snr_gm": 11.210166545186027,
  "snr_total": 13.557442457484262,
  "snr_wm": 26.161850696056703,
  "snrd_csf": 46.55650009030057,
  "snrd_gm": 84.1260953415997,
  "snrd_total": 80.75694080783155,
  "snrd_wm": 111.5882269915944,
  "spacing_x": 1.0,
  "spacing_y": 1.0,
  "spacing_z": 1.0,
  "summary_bg_k": 6.545052737724312,
  "summary_bg_mad": 5.8710302575770505,
  "summary_bg_mean": 5.382617950439453,
  "summary_bg_median": 3.9599497318267822,
  "summary_bg_n": 593917.0,
  "summary_bg_p05": 0.0,
  "summary_bg_p95": 16.019497299194327,
  "summary_bg_stdv": 6.210052490234375,
  "summary_csf_k": 14.311718252133588,
  "summary_csf_mad": 133.47143665359712,
  "summary_csf_mean": 437.8072509765625,
  "summary_csf_median": 417.2178955078125,
  "summary_csf_n": 21810.0,
  "summary_csf_p05": 274.75496978759764,
  "summary_csf_p95": 645.2398376464844,
  "summary_csf_stdv": 126.41488647460938,
  "summary_gm_k": 0.22600660287933616,
  "summary_gm_mad": 64.98750281716329,
  "summary_gm_mean": 760.2285766601562,
  "summary_gm_median": 753.8992919921875,
  "summary_gm_n": 30972.0,
  "summary_gm_p05": 660.7006622314453,
  "summary_gm_p95": 881.3011749267578,
  "summary_gm_stdv": 67.25030517578125,
  "summary_wm_k": 1.255460158842559,
  "summary_wm_mad": 34.32788798794782,
  "summary_wm_mean": 997.8536987304688,
  "summary_wm_median": 1000.0022583007812,
  "summary_wm_n": 240155.0,
  "summary_wm_p05": 931.1790710449219,
  "summary_wm_p95": 1055.3891845703124,
  "summary_wm_stdv": 38.223602294921875,
  "tpm_overlap_csf": 0.15813417732715607,
  "tpm_overlap_gm": 0.44696083664894104,
  "tpm_overlap_wm": 0.4966176748275757,
  "wm2max": 0.6351423822502076
}