{
  "bids_meta": {
    "EchoTime": 0.037,
    "FlipAngle": 8,
    "ParallelAcquisitionTechnique": "SENSE",
    "ParallelReductionFactorInPlan": [
      1,
      1.5
    ],
    "PhaseEncodingDirection": [
      "i-",
      "j-"
    ],
    "PulseSequenceType": "3D fast-field echo",
    "RepetitionTime": 0.081,
    "WaterFatShift": 2.268,
    "dataset": "ds003097",
    "modality": "T1w",
    "run_id": 1,
    "subject_id": "0652"
  },
  "cjv": 0.4907061599220798,
  "cnr": 2.6506346757619177,
  "efc": 0.7782919093673886,
  "fber": 15482.65625,
  "fwhm_avg": 4.387786666666667,
  "fwhm_x": 4.23099,
  "fwhm_y": 4.75904,
  "fwhm_z": 4.17333,
  "icvs_csf": 0.20775048904261104,
  "icvs_gm": 0.4120567772616781,
  "icvs_wm": 0.3801927336957108,
  "inu_med": 0.7963532209396362,
  "inu_range": 0.28151632547378547,
  "provenance": {
    "md5sum": "9bc05927ddacd82bb7fdc302802babf4",
    "settings": {
      "testing": false
    },
    "software": "mriqc",
    "version": "21.0.0rc2",
    "warnings": {
      "large_rot_frame": true,
      "small_air_mask": false
    },
    "webapi_port": null,
    "webapi_url": "https://mriqc.nimh.nih.gov/api/v1"
  },
  "qi_1": 0.0026414803751439384,
  "qi_2": 0.014837824090757007,
  "rpve_csf": 20.68642259397568,
  "rpve_gm": 10.890657782503597,
  "rpve_wm": 14.151253561137223,
  "size_x": 160,
  "size_y": 256,
  "size_z": 256,
  "snr_csf": 3.337786952327462,
  "snr_gm": 10.957569787669307,
  "snr_total": 14.620674342662761,
  "snr_wm": 29.566666287991517,
  "snrd_csf": 33.079002425133986,
  "snrd_gm": 64.81041231267695,
  "snrd_total": 60.115621984848794,
  "snrd_wm": 82.45745121673544,
  "spacing_x": 1.0,
  "spacing_y": 1.0,
  "spacing_z": 1.0,
  "summary_bg_k": 209.47739315275663,
  "summary_bg_mad": 7.9451800522389044,
  "summary_bg_mean": 7.324315071105957,
  "summary_bg_median": 5.377809047698975,
  "summary_bg_n": 326263.0,
  "summary_bg_p05": 0.0,
  "summary_bg_p95": 21.38030605316162,
  "summary_bg_stdv": 15.169286727905273,
  "summary_csf_k": 15.42198877734149,
  "summary_csf_mad": 107.3986676833124,
  "summary_csf_mean": 428.61309814453125,
  "summary_csf_median": 401.1662902832031,
  "summary_csf_n": 42707.0,
  "summary_csf_p05": 288.05682373046875,
  "summary_csf_p95": 631.5525390624999,
  "summary_csf_stdv": 120.18789672851562,
  "summary_gm_k": -0.19386713929907318,
  "summary_gm_mad": 74.12549589151888,
  "summary_gm_mean": 790.6363525390625,
  "summary_gm_median": 785.9896240234375,
  "summary_gm_n": 31945.0,
  "summary_gm_p05": 681.8712158203125,
  "summary_gm_p95": 917.4031982421875,
  "summary_gm_stdv": 71.72916412353516,
  "summary_wm_k": 1.0158120229536785,
  "summary_wm_mad": 30.892900261302106,
  "summary_wm_mean": 998.2346801757812,
  "summary_wm_median": 1000.0044555664062,
  "summary_wm_n": 272072.0,
  "summary_wm_p05": 939.994760131836,
  "summary_wm_p95": 1049.6134765625,
  "summary_wm_stdv": 33.82196044921875,
  "tpm_overlap_csf": 0.1626242995262146,
  "tpm_overlap_gm": 0.45181775093078613,
  "tpm_overlap_wm": 0.5000092387199402,
  "wm2max": 0.6239705524795753
}