{
  "bids_meta": {
    "EchoTime": 0.037,
    "FlipAngle": 8,
    "ParallelAcquisitionTechnique": "SENSE",
    "ParallelReductionFactorInPlan": [
      1,
      1.5
    ],
    "PhaseEncodingDirection": [
      "i-",
      "j-"
    ],
    "PulseSequenceType": "3D fast-field echo",
    "RepetitionTime": 0.081,
    "WaterFatShift": 2.268,
    "dataset": "ds003097",
    "modality": "T1w",
    "run_id": 2,
    "subject_id": "0901"
  },
  "cjv": 0.41302970176241394,
  "cnr": 3.019472883143142,
  "efc": 0.695450922262591,
  "fber": 39416.1875,
  "fwhm_avg": 4.39685,
  "fwhm_x": 4.30141,
  "fwhm_y": 4.71038,
  "fwhm_z": 4.17876,
  "icvs_csf": 0.21090921221917625,
  "icvs_gm": 0.4202127444260676,
  "icvs_wm": 0.36887804335475616,
  "inu_med": 0.9788540601730347,
  "inu_range": 0.34523269534111023,
  "provenance": {
    "md5sum": "9b7484e319d25d236ba3f5a42c1668a2",
    "settings": {
      "testing": false
    },
    "software": "mriqc",
    "version": "21.0.0rc2",
    "warnings": {
      "large_rot_frame": true,
      "small_air_mask": false
    },
    "webapi_port": null,
    "webapi_url": "https://mriqc.nimh.nih.gov/api/v1"
  },
  "qi_1": 0.004438528336876483,
  "qi_2": 0.0031261035374432577,
  "rpve_csf": 20.96278059289622,
  "rpve_gm": 11.1278153359834,
  "rpve_wm": 15.020273071162293,
  "size_x": 160,
  "size_y": 256,
  "size_z": 256,
  "snr_csf": 3.0257571804076013,
  "snr_gm": 12.271095201871901,
  "snr_total": 14.989019731144552,
  "snr_wm": 29.670206811154152,
  "snrd_csf": 48.19713977749528,
  "snrd_gm": 102.52598619397696,
  "snrd_total": 93.98627113203547,
  "snrd_wm": 131.23568742463416,
  "spacing_x": 1.0,
  "spacing_y": 1.0,
  "spacing_z": 1.0,
  "summary_bg_k": 160.66936552371578,
  "summary_bg_mad": 4.992077000094066,
  "summary_bg_mean": 4.974372386932373,
  "summary_bg_median": 3.3671047687530518,
  "summary_bg_n": 531759.0,
  "summary_bg_p05": 0.0,
  "summary_bg_p95": 13.630925559997559,
  "summary_bg_stdv": 7.75841760635376,
  "summary_csf_k": 42.093598496612174,
  "summary_csf_mad": 78.15414889248747,
  "summary_csf_mean": 404.06787109375,
  "summary_csf_median": 367.25762939453125,
  "summary_csf_n": 35175.0,
  "summary_csf_p05": 284.92348327636716,
  "summary_csf_p95": 604.6129821777344,
  "summary_csf_stdv": 121.37537384033203,
  "summary_gm_k": 0.3754637878164284,
  "summary_gm_mad": 60.03303784735127,
  "summary_gm_mean": 784.30908203125,
  "summary_gm_median": 781.23828125,
  "summary_gm_n": 26282.0,
  "summary_gm_p05": 687.9197937011719,
  "summary_gm_p95": 898.6477874755857,
  "summary_gm_stdv": 63.6637077331543,
  "summary_wm_k": 1.2436831894908584,
  "summary_wm_mad": 30.323486536940138,
  "summary_wm_mean": 998.003662109375,
  "summary_wm_median": 1000.0034790039062,
  "summary_wm_n": 245061.0,
  "summary_wm_p05": 939.2906494140625,
  "summary_wm_p95": 1048.18310546875,
  "summary_wm_stdv": 33.70389175415039,
  "tpm_overlap_csf": 0.16803431510925293,
  "tpm_overlap_gm": 0.4532729387283325,
  "tpm_overlap_wm": 0.5022333860397339,
  "wm2max": 0.6467530223058628
}