{
  "bids_meta": {
    "EchoTime": 0.037,
    "FlipAngle": 8,
    "ParallelAcquisitionTechnique": "SENSE",
    "ParallelReductionFactorInPlan": [
      1,
      1.5
    ],
    "PhaseEncodingDirection": [
      "i-",
      "j-"
    ],
    "PulseSequenceType": "3D fast-field echo",
    "RepetitionTime": 0.081,
    "WaterFatShift": 2.268,
    "dataset": "ds003097",
    "modality": "T1w",
    "run_id": 2,
    "subject_id": "0054"
  },
  "cjv": 0.3971442904616684,
  "cnr": 2.963595243902018,
  "efc": 0.7312640338637673,
  "fber": 32823.8046875,
  "fwhm_avg": 4.30951,
  "fwhm_x": 4.19948,
  "fwhm_y": 4.6492,
  "fwhm_z": 4.07985,
  "icvs_csf": 0.20521673985910083,
  "icvs_gm": 0.4310932568857053,
  "icvs_wm": 0.3636900032551939,
  "inu_med": 1.2063473463058472,
  "inu_range": 0.4146413803100586,
  "provenance": {
    "md5sum": "9dc7fb326632b3c07255d296e1401dd3",
    "settings": {
      "testing": false
    },
    "software": "mriqc",
    "version": "21.0.0rc2",
    "warnings": {
      "large_rot_frame": true,
      "small_air_mask": false
    },
    "webapi_port": null,
    "webapi_url": "https://mriqc.nimh.nih.gov/api/v1"
  },
  "qi_1": 0.0,
  "qi_2": 0.015671324689678995,
  "rpve_csf": 21.279217004343607,
  "rpve_gm": 10.827326054647909,
  "rpve_wm": 14.912557890041551,
  "size_x": 160,
  "size_y": 256,
  "size_z": 256,
  "snr_csf": 2.653736812977892,
  "snr_gm": 11.506977567255301,
  "snr_total": 13.825357276851852,
  "snr_wm": 27.31535745032236,
  "snrd_csf": 47.29037729810255,
  "snrd_gm": 96.84517246154974,
  "snrd_total": 89.83286693031873,
  "snrd_wm": 125.36305103130391,
  "spacing_x": 1.0,
  "spacing_y": 1.0,
  "spacing_z": 1.0,
  "summary_bg_k": 6.018984035993254,
  "summary_bg_mad": 5.225926232644025,
  "summary_bg_mean": 6.188884735107422,
  "summary_bg_median": 3.5248336791992188,
  "summary_bg_n": 498359.0,
  "summary_bg_p05": 0.0,
  "summary_bg_p95": 18.124002838134764,
  "summary_bg_stdv": 6.689015865325928,
  "summary_csf_k": 57.22194610347639,
  "summary_csf_mad": 89.41614338729983,
  "summary_csf_mean": 412.302490234375,
  "summary_csf_median": 377.2283630371094,
  "summary_csf_n": 33662.0,
  "summary_csf_p05": 282.17884826660156,
  "summary_csf_p95": 600.4016174316406,
  "summary_csf_stdv": 142.14776611328125,
  "summary_gm_k": 0.7395198279804855,
  "summary_gm_mad": 58.66938586176959,
  "summary_gm_mean": 780.197265625,
  "summary_gm_median": 772.5196533203125,
  "summary_gm_n": 34898.0,
  "summary_gm_p05": 683.8511047363281,
  "summary_gm_p95": 910.3035858154298,
  "summary_gm_stdv": 67.13392639160156,
  "summary_wm_k": 1.3675997245572926,
  "summary_wm_mad": 31.67415308438976,
  "summary_wm_mean": 997.54638671875,
  "summary_wm_median": 1000.0025634765625,
  "summary_wm_n": 249661.0,
  "summary_wm_p05": 932.500732421875,
  "summary_wm_p95": 1051.8572998046875,
  "summary_wm_stdv": 36.60946273803711,
  "tpm_overlap_csf": 0.1638120710849762,
  "tpm_overlap_gm": 0.4588623642921448,
  "tpm_overlap_wm": 0.49772441387176514,
  "wm2max": 0.6555927146488562
}