{
  "bids_meta": {
    "EchoTime": 0.037,
    "FlipAngle": 8,
    "ParallelAcquisitionTechnique": "SENSE",
    "ParallelReductionFactorInPlan": [
      1,
      1.5
    ],
    "PhaseEncodingDirection": [
      "i-",
      "j-"
    ],
    "PulseSequenceType": "3D fast-field echo",
    "RepetitionTime": 0.081,
    "WaterFatShift": 2.268,
    "dataset": "ds003097",
    "modality": "T1w",
    "run_id": 1,
    "subject_id": "0236"
  },
  "cjv": 0.38160904198917395,
  "cnr": 3.363695432065637,
  "efc": 0.7614365326695792,
  "fber": 17302.505859375,
  "fwhm_avg": 4.52181,
  "fwhm_x": 4.46013,
  "fwhm_y": 4.84492,
  "fwhm_z": 4.26038,
  "icvs_csf": 0.19825269704360396,
  "icvs_gm": 0.41736031917040267,
  "icvs_wm": 0.3843869837859934,
  "inu_med": 1.0165197849273682,
  "inu_range": 0.3217671632766723,
  "provenance": {
    "md5sum": "e8c620b7396ef246ff9860e9550cb6c6",
    "settings": {
      "testing": false
    },
    "software": "mriqc",
    "version": "21.0.0rc2",
    "warnings": {
      "large_rot_frame": true,
      "small_air_mask": true
    },
    "webapi_port": null,
    "webapi_url": "https://mriqc.nimh.nih.gov/api/v1"
  },
  "qi_1": 0.001786453589467583,
  "qi_2": 0.02992605824809469,
  "rpve_csf": 24.483594474820688,
  "rpve_gm": 12.427909178283146,
  "rpve_wm": 16.269799131990045,
  "size_x": 160,
  "size_y": 256,
  "size_z": 256,
  "snr_csf": 3.7702377363563344,
  "snr_gm": 12.735998048556674,
  "snr_total": 15.983997631390631,
  "snr_wm": 31.44575710925889,
  "snrd_csf": 39.99013508671956,
  "snrd_gm": 69.11493531355248,
  "snrd_total": 66.31484832640898,
  "snrd_wm": 89.8394745789549,
  "spacing_x": 1.0,
  "spacing_y": 1.0,
  "spacing_z": 1.0,
  "summary_bg_k": 3.4619773404451575,
  "summary_bg_mad": 7.292310427068426,
  "summary_bg_mean": 6.682631015777588,
  "summary_bg_median": 4.918588638305664,
  "summary_bg_n": 283373.0,
  "summary_bg_p05": 0.0,
  "summary_bg_p95": 19.69533767700195,
  "summary_bg_stdv": 6.586922645568848,
  "summary_csf_k": 4.497443523749598,
  "summary_csf_mad": 137.47615482260804,
  "summary_csf_mean": 457.1247253417969,
  "summary_csf_median": 445.1294250488281,
  "summary_csf_n": 20840.0,
  "summary_csf_p05": 292.7359375,
  "summary_csf_p95": 637.9419006347656,
  "summary_csf_stdv": 118.06118774414062,
  "summary_gm_k": 0.1384634246293026,
  "summary_gm_mad": 59.32996912563012,
  "summary_gm_mean": 774.9007568359375,
  "summary_gm_median": 769.3170166015625,
  "summary_gm_n": 29231.0,
  "summary_gm_p05": 686.4433288574219,
  "summary_gm_p95": 884.517333984375,
  "summary_gm_stdv": 60.403892517089844,
  "summary_wm_k": 1.0200101294453825,
  "summary_wm_mad": 28.701302169872225,
  "summary_wm_mean": 998.0259399414062,
  "summary_wm_median": 1000.00146484375,
  "summary_wm_n": 229186.0,
  "summary_wm_p05": 942.0872802734375,
  "summary_wm_p95": 1045.8883972167969,
  "summary_wm_stdv": 31.800769805908203,
  "tpm_overlap_csf": 0.16277898848056793,
  "tpm_overlap_gm": 0.4565008878707886,
  "tpm_overlap_wm": 0.5002627372741699,
  "wm2max": 0.7014262091876595
}