{
  "bids_meta": {
    "EchoTime": 0.037,
    "FlipAngle": 8,
    "ParallelAcquisitionTechnique": "SENSE",
    "ParallelReductionFactorInPlan": [
      1,
      1.5
    ],
    "PhaseEncodingDirection": [
      "i-",
      "j-"
    ],
    "PulseSequenceType": "3D fast-field echo",
    "RepetitionTime": 0.081,
    "WaterFatShift": 2.268,
    "dataset": "ds003097",
    "modality": "T1w",
    "run_id": 1,
    "subject_id": "0501"
  },
  "cjv": 0.4489995386714663,
  "cnr": 2.815779375146172,
  "efc": 0.774408357386699,
  "fber": 14597.1513671875,
  "fwhm_avg": 4.11078,
  "fwhm_x": 4.02499,
  "fwhm_y": 4.44327,
  "fwhm_z": 3.86408,
  "icvs_csf": 0.19407899864154074,
  "icvs_gm": 0.43059225600612977,
  "icvs_wm": 0.3753287453523295,
  "inu_med": 1.2980618476867676,
  "inu_range": 0.44548466205596915,
  "provenance": {
    "md5sum": "0121b09329eb8a71412c55d730a9f579",
    "settings": {
      "testing": false
    },
    "software": "mriqc",
    "version": "21.0.0rc2",
    "warnings": {
      "large_rot_frame": true,
      "small_air_mask": false
    },
    "webapi_port": null,
    "webapi_url": "https://mriqc.nimh.nih.gov/api/v1"
  },
  "qi_1": 3.209379947794086e-05,
  "qi_2": 0.0121648489797099,
  "rpve_csf": 24.613619316904657,
  "rpve_gm": 12.094209901750958,
  "rpve_wm": 16.324318431030505,
  "size_x": 160,
  "size_y": 256,
  "size_z": 256,
  "snr_csf": 2.639069430134049,
  "snr_gm": 11.85949513824263,
  "snr_total": 14.48473647398611,
  "snr_wm": 28.95564485358165,
  "snrd_csf": 33.825758589017475,
  "snrd_gm": 61.263117135759394,
  "snrd_total": 57.64669236441326,
  "snrd_wm": 77.85120136846291,
  "spacing_x": 1.0,
  "spacing_y": 1.0,
  "spacing_z": 1.0,
  "summary_bg_k": 602.7030027694115,
  "summary_bg_mad": 8.415266627639893,
  "summary_bg_mean": 7.943717002868652,
  "summary_bg_median": 5.676011085510254,
  "summary_bg_n": 422961.0,
  "summary_bg_p05": 0.0,
  "summary_bg_p95": 22.603012084960938,
  "summary_bg_stdv": 11.436273574829102,
  "summary_csf_k": 22.323764117097575,
  "summary_csf_mad": 149.24802005717683,
  "summary_csf_mean": 470.0439758300781,
  "summary_csf_median": 434.4939270019531,
  "summary_csf_n": 22587.0,
  "summary_csf_p05": 295.9422973632812,
  "summary_csf_p95": 690.2056518554688,
  "summary_csf_stdv": 164.6354217529297,
  "summary_gm_k": 0.04813080926918145,
  "summary_gm_mad": 64.6997871339517,
  "summary_gm_mean": 791.7632446289062,
  "summary_gm_median": 786.928466796875,
  "summary_gm_n": 24926.0,
  "summary_gm_p05": 690.4376373291016,
  "summary_gm_p95": 912.386962890625,
  "summary_gm_stdv": 66.35296630859375,
  "summary_wm_k": 1.0178757794420834,
  "summary_wm_mad": 30.970767644665393,
  "summary_wm_mean": 999.3468627929688,
  "summary_wm_median": 1000.00341796875,
  "summary_wm_n": 224935.0,
  "summary_wm_p05": 941.5105346679687,
  "summary_wm_p95": 1054.2640625,
  "summary_wm_stdv": 34.535621643066406,
  "tpm_overlap_csf": 0.14406278729438782,
  "tpm_overlap_gm": 0.44628944993019104,
  "tpm_overlap_wm": 0.48246848583221436,
  "wm2max": 0.6275063341583274
}