{
  "bids_meta": {
    "EchoTime": 0.037,
    "FlipAngle": 8,
    "ParallelAcquisitionTechnique": "SENSE",
    "ParallelReductionFactorInPlan": [
      1,
      1.5
    ],
    "PhaseEncodingDirection": [
      "i-",
      "j-"
    ],
    "PulseSequenceType": "3D fast-field echo",
    "RepetitionTime": 0.081,
    "WaterFatShift": 2.268,
    "dataset": "ds003097",
    "modality": "T1w",
    "run_id": 3,
    "subject_id": "0925"
  },
  "cjv": 0.5952536362576631,
  "cnr": 2.148357009687882,
  "efc": 0.7784214754834775,
  "fber": 29386.556640625,
  "fwhm_avg": 4.378146666666667,
  "fwhm_x": 4.38013,
  "fwhm_y": 4.55808,
  "fwhm_z": 4.19623,
  "icvs_csf": 0.2081699319658799,
  "icvs_gm": 0.40337722180779756,
  "icvs_wm": 0.38845284622632253,
  "inu_med": 2.9628005027770996,
  "inu_range": 1.194673013687134,
  "provenance": {
    "md5sum": "4a8aead4bf6c875f16084dbbf42f063a",
    "settings": {
      "testing": false
    },
    "software": "mriqc",
    "version": "21.0.0rc2",
    "warnings": {
      "large_rot_frame": true,
      "small_air_mask": false
    },
    "webapi_port": null,
    "webapi_url": "https://mriqc.nimh.nih.gov/api/v1"
  },
  "qi_1": 0.0034052549345820306,
  "qi_2": 0.003298902275285094,
  "rpve_csf": 21.153818282485325,
  "rpve_gm": 11.236821185120078,
  "rpve_wm": 14.209588015186013,
  "size_x": 160,
  "size_y": 256,
  "size_z": 256,
  "snr_csf": 3.414251555196358,
  "snr_gm": 9.829351749311881,
  "snr_total": 12.750401875242234,
  "snr_wm": 25.007602321218467,
  "snrd_csf": 50.78104973344509,
  "snrd_gm": 92.47862918462441,
  "snrd_total": 86.09344519758601,
  "snrd_wm": 115.02065667468855,
  "spacing_x": 1.0,
  "spacing_y": 1.0,
  "spacing_z": 1.0,
  "summary_bg_k": 6.7630123653485565,
  "summary_bg_mad": 5.695926558945922,
  "summary_bg_mean": 5.553847789764404,
  "summary_bg_median": 3.841844081878662,
  "summary_bg_n": 369239.0,
  "summary_bg_p05": 0.0,
  "summary_bg_p95": 15.64409589767456,
  "summary_bg_stdv": 5.679836750030518,
  "summary_csf_k": 6.157014764333901,
  "summary_csf_mad": 140.39129519239583,
  "summary_csf_mean": 469.23553466796875,
  "summary_csf_median": 441.5036926269531,
  "summary_csf_n": 32310.0,
  "summary_csf_p05": 301.82423400878906,
  "summary_csf_p95": 679.8588684082031,
  "summary_csf_stdv": 129.30999755859375,
  "summary_gm_k": 0.10816023068783975,
  "summary_gm_mad": 80.30308054434062,
  "summary_gm_mean": 812.7208862304688,
  "summary_gm_median": 804.0333251953125,
  "summary_gm_n": 26458.0,
  "summary_gm_p05": 694.8495300292968,
  "summary_gm_p95": 964.6928283691406,
  "summary_gm_stdv": 81.79767608642578,
  "summary_wm_k": 0.8169608413514506,
  "summary_wm_mad": 36.358457597454446,
  "summary_wm_mean": 998.8438720703125,
  "summary_wm_median": 1000.0195922851562,
  "summary_wm_n": 266030.0,
  "summary_wm_p05": 930.8688537597657,
  "summary_wm_p95": 1062.3822875976562,
  "summary_wm_stdv": 39.988548278808594,
  "tpm_overlap_csf": 0.1597842276096344,
  "tpm_overlap_gm": 0.44414639472961426,
  "tpm_overlap_wm": 0.4937710165977478,
  "wm2max": 0.6230830629637844
}