{
  "aor": 0.0031108620689655167,
  "aqi": 0.018991277206896553,
  "bids_meta": {
    "EchoTime": 0.028,
    "EffectiveEchoSpacing": 0.0004491592855135947,
    "FlipAngle": 90,
    "NumberOfVolumesDiscardedByScanner": 1,
    "ParallelReductionFactorInPlane": 0,
    "PhaseEncodingDirection": "j",
    "PulseSequenceType": "gradient echo EPI",
    "RepetitionTime": 2.2,
    "SliceEncodingDirection": "i-",
    "SliceTiming": [
      0.0,
      0.0407,
      0.0815,
      0.1222,
      0.163,
      0.2037,
      0.2444,
      0.2852,
      0.3259,
      0.3667,
      0.4074,
      0.4481,
      0.4889,
      0.5296,
      0.5704,
      0.6111,
      0.6519,
      0.6926,
      0.7333,
      0.7741,
      0.8148,
      0.8556,
      0.8963,
      0.937,
      0.9778,
      1.0185,
      1.0593,
      1.1,
      1.1407,
      1.1815,
      1.2222,
      1.263,
      1.3037,
      1.3444,
      1.3852,
      1.4259,
      1.4667,
      1.5074,
      1.5481,
      1.5889,
      1.6296,
      1.6704,
      1.7111,
      1.7519,
      1.7926,
      1.8333,
      1.8741,
      1.9148,
      1.9556,
      1.9963,
      2.037,
      2.0778,
      2.1185,
      2.1593
    ],
    "TaskName": "moviewatching",
    "TotalReadoutTime": 0.028297034987356466,
    "WaterFatShift": 12.482,
    "dataset": "ds003097",
    "modality": "bold",
    "subject_id": "0250",
    "task_id": "moviewatching"
  },
  "dummy_trs": 0,
  "dvars_nstd": 24.446742437439433,
  "dvars_std": 1.005204995916955,
  "dvars_vstd": 0.9026168393425603,
  "efc": 0.6061523485214521,
  "fber": 2585.551025390625,
  "fd_mean": 0.3569264567792497,
  "fd_num": 153,
  "fd_perc": 52.758620689655174,
  "fwhm_avg": 1.9838174836964837,
  "fwhm_x": 1.8579757844227844,
  "fwhm_y": 2.2434566666666664,
  "fwhm_z": 1.85002,
  "gcor": 0.0427752,
  "gsr_x": 0.03488800302147865,
  "gsr_y": 0.02353520505130291,
  "provenance": {
    "md5sum": "c58174224d4f64616c8b27c15624f5e9",
    "settings": {
      "fd_thres": 0.2,
      "testing": false
    },
    "software": "mriqc",
    "version": "21.0.0rc2",
    "webapi_port": null,
    "webapi_url": "https://mriqc.nimh.nih.gov/api/v1"
  },
  "size_t": 290,
  "size_x": 42,
  "size_y": 64,
  "size_z": 54,
  "snr": 5.717047042423617,
  "spacing_tr": 2.200000047683716,
  "spacing_x": 3.299999952316284,
  "spacing_y": 3.0,
  "spacing_z": 3.0,
  "summary_bg_k": 21.282540692298845,
  "summary_bg_mad": 587.3642177220665,
  "summary_bg_mean": 1436.5843505859375,
  "summary_bg_median": 399.15863037109375,
  "summary_bg_n": 70165.0,
  "summary_bg_p05": 1.0842164993286134,
  "summary_bg_p95": 6211.3595703125075,
  "summary_bg_stdv": 2438.5166015625,
  "summary_fg_k": 2.128980380303502,
  "summary_fg_mad": 3581.3443828060604,
  "summary_fg_mean": 23031.89453125,
  "summary_fg_median": 22700.7265625,
  "summary_fg_n": 38817.0,
  "summary_fg_p05": 17307.1703125,
  "summary_fg_p95": 29467.153515625,
  "summary_fg_stdv": 3970.6572265625,
  "tsnr": 43.157142639160156
}