{
  "bids_meta": {
    "EchoTime": 0.037,
    "FlipAngle": 8,
    "ParallelAcquisitionTechnique": "SENSE",
    "ParallelReductionFactorInPlan": [
      1,
      1.5
    ],
    "PhaseEncodingDirection": [
      "i-",
      "j-"
    ],
    "PulseSequenceType": "3D fast-field echo",
    "RepetitionTime": 0.081,
    "WaterFatShift": 2.268,
    "dataset": "ds003097",
    "modality": "T1w",
    "run_id": 3,
    "subject_id": "0129"
  },
  "cjv": 0.6474083998507263,
  "cnr": 1.9930650510922607,
  "efc": 0.7831680250588946,
  "fber": 15032.0517578125,
  "fwhm_avg": 4.285986666666667,
  "fwhm_x": 4.18592,
  "fwhm_y": 4.57891,
  "fwhm_z": 4.09313,
  "icvs_csf": 0.21529074233401205,
  "icvs_gm": 0.41466134012128153,
  "icvs_wm": 0.37004791754470645,
  "inu_med": 0.7297217845916748,
  "inu_range": 0.3370973765850066,
  "provenance": {
    "md5sum": "48a724f5401ca5e3f1d673239f15619c",
    "settings": {
      "testing": false
    },
    "software": "mriqc",
    "version": "21.0.0rc2",
    "warnings": {
      "large_rot_frame": true,
      "small_air_mask": false
    },
    "webapi_port": null,
    "webapi_url": "https://mriqc.nimh.nih.gov/api/v1"
  },
  "qi_1": 0.0016022906289349978,
  "qi_2": 0.00942251920929004,
  "rpve_csf": 19.810055354599314,
  "rpve_gm": 10.65453556050759,
  "rpve_wm": 14.233869399582066,
  "size_x": 160,
  "size_y": 256,
  "size_z": 256,
  "snr_csf": 3.1126499120972464,
  "snr_gm": 9.619236126838379,
  "snr_total": 12.002681119284915,
  "snr_wm": 23.27615731891912,
  "snrd_csf": 31.0877922086985,
  "snrd_gm": 60.06348984770828,
  "snrd_total": 55.07566188307365,
  "snrd_wm": 74.07570359281416,
  "spacing_x": 1.0,
  "spacing_y": 1.0,
  "spacing_z": 1.0,
  "summary_bg_k": 2.6792677518750736,
  "summary_bg_mad": 8.8443311520255,
  "summary_bg_mean": 7.854629039764404,
  "summary_bg_median": 5.9654107093811035,
  "summary_bg_n": 306438.0,
  "summary_bg_p05": 0.0,
  "summary_bg_p95": 23.562747192382812,
  "summary_bg_stdv": 7.545168399810791,
  "summary_csf_k": 15.566334868808305,
  "summary_csf_mad": 113.74266502411214,
  "summary_csf_mean": 457.5008544921875,
  "summary_csf_median": 419.6847229003906,
  "summary_csf_n": 32003.0,
  "summary_csf_p05": 304.8794677734375,
  "summary_csf_p95": 692.8017272949218,
  "summary_csf_stdv": 134.82986450195312,
  "summary_gm_k": 0.15660084890323622,
  "summary_gm_mad": 82.49617173492852,
  "summary_gm_mean": 820.7962036132812,
  "summary_gm_median": 810.856201171875,
  "summary_gm_n": 25235.0,
  "summary_gm_p05": 700.2267028808594,
  "summary_gm_p95": 975.8933837890625,
  "summary_gm_stdv": 84.29360961914062,
  "summary_wm_k": 0.8141487701850334,
  "summary_wm_mad": 39.97062642418768,
  "summary_wm_mean": 1002.0768432617188,
  "summary_wm_median": 1000.0208740234375,
  "summary_wm_n": 253746.0,
  "summary_wm_p05": 934.8771362304688,
  "summary_wm_p95": 1074.8049621582031,
  "summary_wm_stdv": 42.96323013305664,
  "tpm_overlap_csf": 0.17513582110404968,
  "tpm_overlap_gm": 0.4620387554168701,
  "tpm_overlap_wm": 0.5072851181030273,
  "wm2max": 0.5536757855049603
}