{
  "bids_meta": {
    "EchoTime": 0.037,
    "FlipAngle": 8,
    "ParallelAcquisitionTechnique": "SENSE",
    "ParallelReductionFactorInPlan": [
      1,
      1.5
    ],
    "PhaseEncodingDirection": [
      "i-",
      "j-"
    ],
    "PulseSequenceType": "3D fast-field echo",
    "RepetitionTime": 0.081,
    "WaterFatShift": 2.268,
    "dataset": "ds003097",
    "modality": "T1w",
    "run_id": 2,
    "subject_id": "0644"
  },
  "cjv": 0.43151179456089395,
  "cnr": 2.870278473907297,
  "efc": 0.7425662676846706,
  "fber": 23730.09765625,
  "fwhm_avg": 4.334556666666667,
  "fwhm_x": 4.20982,
  "fwhm_y": 4.72247,
  "fwhm_z": 4.07138,
  "icvs_csf": 0.19071312665627993,
  "icvs_gm": 0.42535628843904183,
  "icvs_wm": 0.38393058490467824,
  "inu_med": 0.8551024198532104,
  "inu_range": 0.29770820140838605,
  "provenance": {
    "md5sum": "f4054857f63d2e5a9deef2e9dc055846",
    "settings": {
      "testing": false
    },
    "software": "mriqc",
    "version": "21.0.0rc2",
    "warnings": {
      "large_rot_frame": true,
      "small_air_mask": false
    },
    "webapi_port": null,
    "webapi_url": "https://mriqc.nimh.nih.gov/api/v1"
  },
  "qi_1": 0.003940366355311408,
  "qi_2": 0.007868536552371918,
  "rpve_csf": 23.53319392676176,
  "rpve_gm": 11.542711746065846,
  "rpve_wm": 15.184867754527644,
  "size_x": 160,
  "size_y": 256,
  "size_z": 256,
  "snr_csf": 2.8183671300876925,
  "snr_gm": 10.96664223357773,
  "snr_total": 14.521581069754774,
  "snr_wm": 29.7797338455989,
  "snrd_csf": 39.32830058249996,
  "snrd_gm": 77.06249267550584,
  "snrd_total": 71.94545031078069,
  "snrd_wm": 99.44555767433627,
  "spacing_x": 1.0,
  "spacing_y": 1.0,
  "spacing_z": 1.0,
  "summary_bg_k": 5.160261478442614,
  "summary_bg_mad": 6.587917569588277,
  "summary_bg_mean": 5.111044406890869,
  "summary_bg_median": 4.443482875823975,
  "summary_bg_n": 400265.0,
  "summary_bg_p05": 0.0,
  "summary_bg_p95": 13.52919692993164,
  "summary_bg_stdv": 5.358067989349365,
  "summary_csf_k": 49.90909632605103,
  "summary_csf_mad": 89.58219411184558,
  "summary_csf_mean": 425.9849548339844,
  "summary_csf_median": 395.47735595703125,
  "summary_csf_n": 25209.0,
  "summary_csf_p05": 288.0900512695313,
  "summary_csf_p95": 619.5542358398437,
  "summary_csf_stdv": 140.31866455078125,
  "summary_gm_k": 0.28399263161215993,
  "summary_gm_mad": 67.22050047615704,
  "summary_gm_mean": 782.4830322265625,
  "summary_gm_median": 774.9246826171875,
  "summary_gm_n": 30591.0,
  "summary_gm_p05": 680.6185302734375,
  "summary_gm_p95": 915.9501037597656,
  "summary_gm_stdv": 70.66082763671875,
  "summary_wm_k": 1.1774722556509012,
  "summary_wm_mad": 29.903970918959672,
  "summary_wm_mean": 998.716064453125,
  "summary_wm_median": 1000.0042114257812,
  "summary_wm_n": 257207.0,
  "summary_wm_p05": 941.7521667480469,
  "summary_wm_p95": 1050.700830078125,
  "summary_wm_stdv": 33.579959869384766,
  "tpm_overlap_csf": 0.18131989240646362,
  "tpm_overlap_gm": 0.463327020406723,
  "tpm_overlap_wm": 0.5215368270874023,
  "wm2max": 0.6843852106114489
}