{
  "bids_meta": {
    "EchoTime": 0.037,
    "FlipAngle": 8,
    "ParallelAcquisitionTechnique": "SENSE",
    "ParallelReductionFactorInPlan": [
      1,
      1.5
    ],
    "PhaseEncodingDirection": [
      "i-",
      "j-"
    ],
    "PulseSequenceType": "3D fast-field echo",
    "RepetitionTime": 0.081,
    "WaterFatShift": 2.268,
    "dataset": "ds003097",
    "modality": "T1w",
    "run_id": 2,
    "subject_id": "0168"
  },
  "cjv": 0.3994320587394079,
  "cnr": 3.165326452144724,
  "efc": 0.5865356359077043,
  "fber": 36496.1796875,
  "fwhm_avg": 4.126613333333333,
  "fwhm_x": 4.03054,
  "fwhm_y": 4.42321,
  "fwhm_z": 3.92609,
  "icvs_csf": 0.1861003220254652,
  "icvs_gm": 0.43599367635421066,
  "icvs_wm": 0.3779060016203241,
  "inu_med": 1.2288933992385864,
  "inu_range": 0.33855123519897456,
  "provenance": {
    "md5sum": "6d03ff41de6d298cd133430bc611c40b",
    "settings": {
      "testing": false
    },
    "software": "mriqc",
    "version": "21.0.0rc2",
    "warnings": {
      "large_rot_frame": true,
      "small_air_mask": false
    },
    "webapi_port": null,
    "webapi_url": "https://mriqc.nimh.nih.gov/api/v1"
  },
  "qi_1": 0.00837428438875201,
  "qi_2": 0.005205065517934871,
  "rpve_csf": 32.064356313774724,
  "rpve_gm": 15.197239668936371,
  "rpve_wm": 20.53405136571967,
  "size_x": 160,
  "size_y": 256,
  "size_z": 256,
  "snr_csf": 3.169766085069392,
  "snr_gm": 11.932017201252755,
  "snr_total": 15.303180710090556,
  "snr_wm": 30.807758843949518,
  "snrd_csf": 50.56350112445575,
  "snrd_gm": 95.14501624403196,
  "snrd_total": 89.72279982927493,
  "snrd_wm": 123.45988211933707,
  "spacing_x": 1.0,
  "spacing_y": 1.0,
  "spacing_z": 1.0,
  "summary_bg_k": 12.367751788238005,
  "summary_bg_mad": 5.306539447981662,
  "summary_bg_mean": 4.298434257507324,
  "summary_bg_median": 3.5792064666748047,
  "summary_bg_n": 1372494.0,
  "summary_bg_p05": 0.0,
  "summary_bg_p95": 14.314015436172484,
  "summary_bg_stdv": 4.984402179718018,
  "summary_csf_k": 28.091600506728145,
  "summary_csf_mad": 111.94434020182443,
  "summary_csf_mean": 432.4648132324219,
  "summary_csf_median": 409.559326171875,
  "summary_csf_n": 15099.0,
  "summary_csf_p05": 285.56053466796874,
  "summary_csf_p95": 617.0776855468749,
  "summary_csf_stdv": 129.2037811279297,
  "summary_gm_k": 0.1278790223460624,
  "summary_gm_mad": 62.45778563458069,
  "summary_gm_mean": 776.9732055664062,
  "summary_gm_median": 770.6651611328125,
  "summary_gm_n": 23041.0,
  "summary_gm_p05": 682.4583129882812,
  "summary_gm_p95": 896.5744018554688,
  "summary_gm_stdv": 64.58660125732422,
  "summary_wm_k": 1.0476824788223356,
  "summary_wm_mad": 29.15099648901673,
  "summary_wm_mean": 998.2313842773438,
  "summary_wm_median": 1000.0127563476562,
  "summary_wm_n": 178297.0,
  "summary_wm_p05": 941.4194458007812,
  "summary_wm_p95": 1047.34716796875,
  "summary_wm_stdv": 32.459678649902344,
  "tpm_overlap_csf": 0.16743959486484528,
  "tpm_overlap_gm": 0.46269911527633667,
  "tpm_overlap_wm": 0.5033106207847595,
  "wm2max": 0.6818557609081839
}