{
  "bids_meta": {
    "EchoTime": 0.037,
    "FlipAngle": 8,
    "ParallelAcquisitionTechnique": "SENSE",
    "ParallelReductionFactorInPlan": [
      1,
      1.5
    ],
    "PhaseEncodingDirection": [
      "i-",
      "j-"
    ],
    "PulseSequenceType": "3D fast-field echo",
    "RepetitionTime": 0.081,
    "WaterFatShift": 2.268,
    "dataset": "ds003097",
    "modality": "T1w",
    "run_id": 2,
    "subject_id": "0772"
  },
  "cjv": 0.8263100760316077,
  "cnr": 1.669520516856668,
  "efc": 0.776003119010144,
  "fber": 15926.2314453125,
  "fwhm_avg": 4.0177233333333335,
  "fwhm_x": 3.96269,
  "fwhm_y": 4.27287,
  "fwhm_z": 3.81761,
  "icvs_csf": 0.22260942273225034,
  "icvs_gm": 0.43411017330038526,
  "icvs_wm": 0.3432804039673644,
  "inu_med": 1.3004276752471924,
  "inu_range": 0.6532366275787351,
  "provenance": {
    "md5sum": "efb09f2a029347b3be609dbcdf4b116a",
    "settings": {
      "testing": false
    },
    "software": "mriqc",
    "version": "21.0.0rc2",
    "warnings": {
      "large_rot_frame": true,
      "small_air_mask": true
    },
    "webapi_port": null,
    "webapi_url": "https://mriqc.nimh.nih.gov/api/v1"
  },
  "qi_1": 0.00017797829078755394,
  "qi_2": 0.007136562813654399,
  "rpve_csf": 23.37173754365476,
  "rpve_gm": 12.575339580535708,
  "rpve_wm": 18.14099486616287,
  "size_x": 160,
  "size_y": 256,
  "size_z": 256,
  "snr_csf": 2.6440084811405518,
  "snr_gm": 9.751603074532827,
  "snr_total": 10.001850433814134,
  "snr_wm": 17.609939745769022,
  "snrd_csf": 32.1276149104902,
  "snrd_gm": 63.082017124192866,
  "snrd_total": 57.10475779941391,
  "snrd_wm": 76.10464136355867,
  "spacing_x": 1.0,
  "spacing_y": 1.0,
  "spacing_z": 1.0,
  "summary_bg_k": 3.6352866649563547,
  "summary_bg_mad": 8.608594690213046,
  "summary_bg_mean": 7.696504592895508,
  "summary_bg_median": 5.806408882141113,
  "summary_bg_n": 255623.0,
  "summary_bg_p05": 0.0,
  "summary_bg_p95": 23.07450313568115,
  "summary_bg_stdv": 7.45597505569458,
  "summary_csf_k": 27.975187039524727,
  "summary_csf_mad": 137.2387068110505,
  "summary_csf_mean": 465.6199951171875,
  "summary_csf_median": 422.1618957519531,
  "summary_csf_n": 26675.0,
  "summary_csf_p05": 301.17567138671876,
  "summary_csf_p95": 699.4557800292968,
  "summary_csf_stdv": 159.6643829345703,
  "summary_gm_k": -0.3332626046589571,
  "summary_gm_mad": 89.88651486751174,
  "summary_gm_mean": 831.823974609375,
  "summary_gm_median": 828.9075927734375,
  "summary_gm_n": 21700.0,
  "summary_gm_p05": 700.1777252197265,
  "summary_gm_p95": 978.957583618164,
  "summary_gm_stdv": 85.00022888183594,
  "summary_wm_k": 0.5557061696562235,
  "summary_wm_mad": 51.51110653468917,
  "summary_wm_mean": 998.40625,
  "summary_wm_median": 1000.0269165039062,
  "summary_wm_n": 176937.0,
  "summary_wm_p05": 895.4008911132812,
  "summary_wm_p95": 1087.0884033203124,
  "summary_wm_stdv": 56.787479400634766,
  "tpm_overlap_csf": 0.1794963777065277,
  "tpm_overlap_gm": 0.47463059425354004,
  "tpm_overlap_wm": 0.5042364001274109,
  "wm2max": 0.5654965290244507
}