{
  "bids_meta": {
    "EchoTime": 0.037,
    "FlipAngle": 8,
    "ParallelAcquisitionTechnique": "SENSE",
    "ParallelReductionFactorInPlan": [
      1,
      1.5
    ],
    "PhaseEncodingDirection": [
      "i-",
      "j-"
    ],
    "PulseSequenceType": "3D fast-field echo",
    "RepetitionTime": 0.081,
    "WaterFatShift": 2.268,
    "dataset": "ds003097",
    "modality": "T1w",
    "run_id": 3,
    "subject_id": "0415"
  },
  "cjv": 0.47450597267086997,
  "cnr": 2.77060994914543,
  "efc": 0.7379029166505808,
  "fber": 28244.162109375,
  "fwhm_avg": 4.141766666666666,
  "fwhm_x": 4.0457,
  "fwhm_y": 4.38286,
  "fwhm_z": 3.99674,
  "icvs_csf": 0.2000595746493144,
  "icvs_gm": 0.43190769880482066,
  "icvs_wm": 0.36803272654586494,
  "inu_med": 1.2066477537155151,
  "inu_range": 0.39024516344070426,
  "provenance": {
    "md5sum": "b94a0a551bfd4bbf62134492478d9b51",
    "settings": {
      "testing": false
    },
    "software": "mriqc",
    "version": "21.0.0rc2",
    "warnings": {
      "large_rot_frame": true,
      "small_air_mask": false
    },
    "webapi_port": null,
    "webapi_url": "https://mriqc.nimh.nih.gov/api/v1"
  },
  "qi_1": 0.0010207659294961412,
  "qi_2": 0.0031748739172600734,
  "rpve_csf": 24.791111195814793,
  "rpve_gm": 12.370581915781683,
  "rpve_wm": 16.934736797569514,
  "size_x": 160,
  "size_y": 256,
  "size_z": 256,
  "snr_csf": 1.8973980649190967,
  "snr_gm": 11.865497318882483,
  "snr_total": 13.89304824507864,
  "snr_wm": 27.91624935143434,
  "snrd_csf": 44.9763285703777,
  "snrd_gm": 91.51563121085104,
  "snrd_total": 84.11399585020206,
  "snrd_wm": 115.85002776937742,
  "spacing_x": 1.0,
  "spacing_y": 1.0,
  "spacing_z": 1.0,
  "summary_bg_k": 7.774861354402317,
  "summary_bg_mad": 5.655028579380464,
  "summary_bg_mean": 5.3823747634887695,
  "summary_bg_median": 3.8142588138580322,
  "summary_bg_n": 399642.0,
  "summary_bg_p05": 0.0,
  "summary_bg_p95": 15.40850887298584,
  "summary_bg_stdv": 5.695152759552002,
  "summary_csf_k": 45.47974153766165,
  "summary_csf_mad": 104.38649849096646,
  "summary_csf_mean": 434.3144836425781,
  "summary_csf_median": 388.22821044921875,
  "summary_csf_n": 23695.0,
  "summary_csf_p05": 274.6824005126953,
  "summary_csf_p95": 642.5932678222656,
  "summary_csf_stdv": 204.6065216064453,
  "summary_gm_k": -0.042133871975162496,
  "summary_gm_mad": 66.63307907104051,
  "summary_gm_mean": 793.7747802734375,
  "summary_gm_median": 789.94775390625,
  "summary_gm_n": 36216.0,
  "summary_gm_p05": 691.3761901855469,
  "summary_gm_p95": 910.3384857177734,
  "summary_gm_stdv": 66.57427215576172,
  "summary_wm_k": 0.8567255882112685,
  "summary_wm_mad": 33.03712638853596,
  "summary_wm_mean": 996.9354858398438,
  "summary_wm_median": 999.9982299804688,
  "summary_wm_n": 207865.0,
  "summary_wm_p05": 932.2511108398437,
  "summary_wm_p95": 1049.122802734375,
  "summary_wm_stdv": 35.82128143310547,
  "tpm_overlap_csf": 0.1507183462381363,
  "tpm_overlap_gm": 0.45474839210510254,
  "tpm_overlap_wm": 0.48703259229660034,
  "wm2max": 0.7206296728291266
}