{
  "bids_meta": {
    "EchoTime": 0.037,
    "FlipAngle": 8,
    "ParallelAcquisitionTechnique": "SENSE",
    "ParallelReductionFactorInPlan": [
      1,
      1.5
    ],
    "PhaseEncodingDirection": [
      "i-",
      "j-"
    ],
    "PulseSequenceType": "3D fast-field echo",
    "RepetitionTime": 0.081,
    "WaterFatShift": 2.268,
    "dataset": "ds003097",
    "modality": "T1w",
    "run_id": 3,
    "subject_id": "0781"
  },
  "cjv": 0.7008590444208228,
  "cnr": 1.8050078305178001,
  "efc": 0.7699138784165026,
  "fber": 5023.732421875,
  "fwhm_avg": 4.1596,
  "fwhm_x": 4.09593,
  "fwhm_y": 4.43252,
  "fwhm_z": 3.95035,
  "icvs_csf": 0.2283859479448702,
  "icvs_gm": 0.41916645160899896,
  "icvs_wm": 0.3524476004461309,
  "inu_med": 1.3382827043533325,
  "inu_range": 0.5649338364601135,
  "provenance": {
    "md5sum": "c6bcc1db54f7e68e869ea83103874d98",
    "settings": {
      "testing": false
    },
    "software": "mriqc",
    "version": "21.0.0rc2",
    "warnings": {
      "large_rot_frame": true,
      "small_air_mask": false
    },
    "webapi_port": null,
    "webapi_url": "https://mriqc.nimh.nih.gov/api/v1"
  },
  "qi_1": 0.0,
  "qi_2": 0.009956393914925208,
  "rpve_csf": 20.031229947760604,
  "rpve_gm": 11.137382051905263,
  "rpve_wm": 15.505581119325315,
  "size_x": 160,
  "size_y": 256,
  "size_z": 256,
  "snr_csf": 3.431887397493662,
  "snr_gm": 9.555437049947436,
  "snr_total": 12.458947925193181,
  "snr_wm": 24.389519328138444,
  "snrd_csf": 36.909604285408726,
  "snrd_gm": 73.4211921622643,
  "snrd_total": 66.39165753649974,
  "snrd_wm": 88.84417616182618,
  "spacing_x": 1.0,
  "spacing_y": 1.0,
  "spacing_z": 1.0,
  "summary_bg_k": 6.33309019579074,
  "summary_bg_mad": 7.374063261649795,
  "summary_bg_mean": 8.9092378616333,
  "summary_bg_median": 4.973730087280273,
  "summary_bg_n": 453678.0,
  "summary_bg_p05": 0.0,
  "summary_bg_p95": 28.800428295135454,
  "summary_bg_stdv": 9.436942100524902,
  "summary_csf_k": 0.29021197463140247,
  "summary_csf_mad": 109.90205202619865,
  "summary_csf_mean": 443.1376647949219,
  "summary_csf_median": 415.4459533691406,
  "summary_csf_n": 39069.0,
  "summary_csf_p05": 290.15150756835936,
  "summary_csf_p95": 666.7018310546874,
  "summary_csf_stdv": 121.05310821533203,
  "summary_gm_k": -0.04054882946357763,
  "summary_gm_mad": 83.72938114861226,
  "summary_gm_mean": 834.098876953125,
  "summary_gm_median": 826.4119262695312,
  "summary_gm_n": 25947.0,
  "summary_gm_p05": 705.1491760253906,
  "summary_gm_p95": 994.3587585449217,
  "summary_gm_stdv": 86.484375,
  "summary_wm_k": 0.6371587632540163,
  "summary_wm_mad": 37.93802077037464,
  "summary_wm_mean": 1000.2750854492188,
  "summary_wm_median": 1000.0094604492188,
  "summary_wm_n": 224051.0,
  "summary_wm_p05": 933.1618957519531,
  "summary_wm_p95": 1067.91650390625,
  "summary_wm_stdv": 41.00151443481445,
  "tpm_overlap_csf": 0.16469287872314453,
  "tpm_overlap_gm": 0.4554690420627594,
  "tpm_overlap_wm": 0.5016815662384033,
  "wm2max": 0.6077860112310558
}