{
  "bids_meta": {
    "EchoTime": 0.037,
    "FlipAngle": 8,
    "ParallelAcquisitionTechnique": "SENSE",
    "ParallelReductionFactorInPlan": [
      1,
      1.5
    ],
    "PhaseEncodingDirection": [
      "i-",
      "j-"
    ],
    "PulseSequenceType": "3D fast-field echo",
    "RepetitionTime": 0.081,
    "WaterFatShift": 2.268,
    "dataset": "ds003097",
    "modality": "T1w",
    "run_id": 3,
    "subject_id": "0154"
  },
  "cjv": 0.3989550374502895,
  "cnr": 2.997502615652555,
  "efc": 0.6487772422502498,
  "fber": 25946.974609375,
  "fwhm_avg": 4.2073366666666665,
  "fwhm_x": 4.13416,
  "fwhm_y": 4.49737,
  "fwhm_z": 3.99048,
  "icvs_csf": 0.1972050376879328,
  "icvs_gm": 0.43984007492518284,
  "icvs_wm": 0.36295488738688436,
  "inu_med": 1.0281181335449219,
  "inu_range": 0.35109248757362355,
  "provenance": {
    "md5sum": "25fdbbde37a701e87a719c2571fe00bf",
    "settings": {
      "testing": false
    },
    "software": "mriqc",
    "version": "21.0.0rc2",
    "warnings": {
      "large_rot_frame": true,
      "small_air_mask": false
    },
    "webapi_port": null,
    "webapi_url": "https://mriqc.nimh.nih.gov/api/v1"
  },
  "qi_1": 0.00737145191071085,
  "qi_2": 0.02681790719108306,
  "rpve_csf": 26.72139658424544,
  "rpve_gm": 13.098111993351946,
  "rpve_wm": 18.280471725111443,
  "size_x": 160,
  "size_y": 256,
  "size_z": 256,
  "snr_csf": 2.034980496975662,
  "snr_gm": 11.540898907177793,
  "snr_total": 13.520958758158487,
  "snr_wm": 26.98699687032201,
  "snrd_csf": 42.83949780234423,
  "snrd_gm": 82.89134322266852,
  "snrd_total": 77.77681514547383,
  "snrd_wm": 107.59960441140876,
  "spacing_x": 1.0,
  "spacing_y": 1.0,
  "spacing_z": 1.0,
  "summary_bg_k": 7.933733593151613,
  "summary_bg_mad": 6.0886667803773165,
  "summary_bg_mean": 5.596190452575684,
  "summary_bg_median": 4.106743335723877,
  "summary_bg_n": 873167.0,
  "summary_bg_p05": 0.0,
  "summary_bg_p95": 16.731982612609862,
  "summary_bg_stdv": 6.3352274894714355,
  "summary_csf_k": 45.67606675187625,
  "summary_csf_mad": 103.9289767125995,
  "summary_csf_mean": 445.2326965332031,
  "summary_csf_median": 398.1391296386719,
  "summary_csf_n": 25174.0,
  "summary_csf_p05": 290.98774871826174,
  "summary_csf_p95": 641.8078521728515,
  "summary_csf_stdv": 195.6437530517578,
  "summary_gm_k": 0.35100919793669005,
  "summary_gm_mad": 60.44422830638993,
  "summary_gm_mean": 779.6898803710938,
  "summary_gm_median": 770.3705444335938,
  "summary_gm_n": 24234.0,
  "summary_gm_p05": 685.3857482910156,
  "summary_gm_p95": 908.1169219970702,
  "summary_gm_stdv": 66.74996948242188,
  "summary_wm_k": 1.5747165187324423,
  "summary_wm_mad": 31.16867115124936,
  "summary_wm_mean": 997.0133056640625,
  "summary_wm_median": 1000.002685546875,
  "summary_wm_n": 192553.0,
  "summary_wm_p05": 928.7232055664062,
  "summary_wm_p95": 1050.456689453125,
  "summary_wm_stdv": 37.05488586425781,
  "tpm_overlap_csf": 0.15958812832832336,
  "tpm_overlap_gm": 0.46811071038246155,
  "tpm_overlap_wm": 0.505961000919342,
  "wm2max": 0.6655559566886925
}