{
  "bids_meta": {
    "EchoTime": 0.037,
    "FlipAngle": 8,
    "ParallelAcquisitionTechnique": "SENSE",
    "ParallelReductionFactorInPlan": [
      1,
      1.5
    ],
    "PhaseEncodingDirection": [
      "i-",
      "j-"
    ],
    "PulseSequenceType": "3D fast-field echo",
    "RepetitionTime": 0.081,
    "WaterFatShift": 2.268,
    "dataset": "ds003097",
    "modality": "T1w",
    "run_id": 3,
    "subject_id": "0331"
  },
  "cjv": 0.5101505700983672,
  "cnr": 2.577253136878894,
  "efc": 0.6175470592512168,
  "fber": 38889.57421875,
  "fwhm_avg": 4.297716666666666,
  "fwhm_x": 4.06699,
  "fwhm_y": 4.68267,
  "fwhm_z": 4.14349,
  "icvs_csf": 0.21531140772151047,
  "icvs_gm": 0.40191481283208486,
  "icvs_wm": 0.38277377944640467,
  "inu_med": 0.9654623866081238,
  "inu_range": 0.33309847116470337,
  "provenance": {
    "md5sum": "39300b8436b2ec0bdbc1baedfa640e7c",
    "settings": {
      "testing": false
    },
    "software": "mriqc",
    "version": "21.0.0rc2",
    "warnings": {
      "large_rot_frame": true,
      "small_air_mask": false
    },
    "webapi_port": null,
    "webapi_url": "https://mriqc.nimh.nih.gov/api/v1"
  },
  "qi_1": 2.044934016795725e-05,
  "qi_2": 0.011050930560484092,
  "rpve_csf": 23.02716846084513,
  "rpve_gm": 12.498756301787944,
  "rpve_wm": 15.933038558615957,
  "size_x": 160,
  "size_y": 256,
  "size_z": 256,
  "snr_csf": 3.5339033913857194,
  "snr_gm": 11.067489706716161,
  "snr_total": 12.40891204001729,
  "snr_wm": 22.625343021949988,
  "snrd_csf": 50.396047689499525,
  "snrd_gm": 100.4556712282787,
  "snrd_total": 93.10340144106844,
  "snrd_wm": 128.45848540542707,
  "spacing_x": 1.0,
  "spacing_y": 1.0,
  "spacing_z": 1.0,
  "summary_bg_k": 9.802596574301205,
  "summary_bg_mad": 5.1001520699743645,
  "summary_bg_mean": 10.135149955749512,
  "summary_bg_median": 3.440000295639038,
  "summary_bg_n": 1479265.0,
  "summary_bg_p05": 0.0,
  "summary_bg_p95": 40.67546615600586,
  "summary_bg_stdv": 14.438109397888184,
  "summary_csf_k": 33.07668289870309,
  "summary_csf_mad": 102.10481675033478,
  "summary_csf_mean": 410.4032287597656,
  "summary_csf_median": 392.32672119140625,
  "summary_csf_n": 28740.0,
  "summary_csf_p05": 267.9926513671875,
  "summary_csf_p95": 598.9413818359375,
  "summary_csf_stdv": 111.01602172851562,
  "summary_gm_k": 0.08770546664717971,
  "summary_gm_mad": 70.30307155607606,
  "summary_gm_mean": 786.3228149414062,
  "summary_gm_median": 782.034423828125,
  "summary_gm_n": 19307.0,
  "summary_gm_p05": 677.0978576660157,
  "summary_gm_p95": 908.2959106445313,
  "summary_gm_stdv": 70.65867614746094,
  "summary_wm_k": 0.7885277599473866,
  "summary_wm_mad": 40.908880886014785,
  "summary_wm_mean": 1001.3175048828125,
  "summary_wm_median": 1000.03271484375,
  "summary_wm_n": 227012.0,
  "summary_wm_p05": 931.0037536621094,
  "summary_wm_p95": 1075.8126953125,
  "summary_wm_stdv": 44.1995735168457,
  "tpm_overlap_csf": 0.16638943552970886,
  "tpm_overlap_gm": 0.43457815051078796,
  "tpm_overlap_wm": 0.5001562237739563,
  "wm2max": 0.6295195977722302
}