{
  "bids_meta": {
    "EchoTime": 0.037,
    "FlipAngle": 8,
    "ParallelAcquisitionTechnique": "SENSE",
    "ParallelReductionFactorInPlan": [
      1,
      1.5
    ],
    "PhaseEncodingDirection": [
      "i-",
      "j-"
    ],
    "PulseSequenceType": "3D fast-field echo",
    "RepetitionTime": 0.081,
    "WaterFatShift": 2.268,
    "dataset": "ds003097",
    "modality": "T1w",
    "run_id": 2,
    "subject_id": "0108"
  },
  "cjv": 0.42988960816857763,
  "cnr": 2.9345242411372725,
  "efc": 0.6438278628113736,
  "fber": 43696.515625,
  "fwhm_avg": 4.106583333333333,
  "fwhm_x": 3.99064,
  "fwhm_y": 4.38747,
  "fwhm_z": 3.94164,
  "icvs_csf": 0.1713084773117574,
  "icvs_gm": 0.45694578568334543,
  "icvs_wm": 0.37174573700489716,
  "inu_med": 1.106130599975586,
  "inu_range": 0.39362841844558716,
  "provenance": {
    "md5sum": "eab0b8484630a03698fe94ae13bba164",
    "settings": {
      "testing": false
    },
    "software": "mriqc",
    "version": "21.0.0rc2",
    "warnings": {
      "large_rot_frame": true,
      "small_air_mask": false
    },
    "webapi_port": null,
    "webapi_url": "https://mriqc.nimh.nih.gov/api/v1"
  },
  "qi_1": 0.01808163861048944,
  "qi_2": 0.01793678989749846,
  "rpve_csf": 28.17947190895654,
  "rpve_gm": 12.044948564230562,
  "rpve_wm": 16.743686238656156,
  "size_x": 160,
  "size_y": 256,
  "size_z": 256,
  "snr_csf": 2.4608760356598283,
  "snr_gm": 12.325514004325012,
  "snr_total": 13.117579949530963,
  "snr_wm": 24.566349808608045,
  "snrd_csf": 60.103004946232986,
  "snrd_gm": 102.02385973686613,
  "snrd_total": 97.71908697830132,
  "snrd_wm": 131.0303962518048,
  "spacing_x": 1.0,
  "spacing_y": 1.0,
  "spacing_z": 1.0,
  "summary_bg_k": 7.9811676543714825,
  "summary_bg_mad": 4.999910821954981,
  "summary_bg_mean": 5.624459266662598,
  "summary_bg_median": 3.3723886013031006,
  "summary_bg_n": 945549.0,
  "summary_bg_p05": 0.0,
  "summary_bg_p95": 19.742002487182614,
  "summary_bg_stdv": 6.573391437530518,
  "summary_csf_k": 36.64477085003548,
  "summary_csf_mad": 167.46011966009547,
  "summary_csf_mean": 482.7336730957031,
  "summary_csf_median": 458.6978759765625,
  "summary_csf_n": 16706.0,
  "summary_csf_p05": 296.34093475341797,
  "summary_csf_p95": 685.5421295166016,
  "summary_csf_stdv": 186.39059448242188,
  "summary_gm_k": 0.2508156684618892,
  "summary_gm_mad": 59.927480261420676,
  "summary_gm_mean": 785.0447998046875,
  "summary_gm_median": 778.632080078125,
  "summary_gm_n": 38887.0,
  "summary_gm_p05": 691.4173522949219,
  "summary_gm_p95": 899.6883544921874,
  "summary_gm_stdv": 63.17156982421875,
  "summary_wm_k": 1.1846577049778526,
  "summary_wm_mad": 35.23885945606891,
  "summary_wm_mean": 997.4568481445312,
  "summary_wm_median": 1000.0059814453125,
  "summary_wm_n": 200655.0,
  "summary_wm_p05": 924.4684997558594,
  "summary_wm_p95": 1058.6737915039062,
  "summary_wm_stdv": 40.70623016357422,
  "tpm_overlap_csf": 0.15565592050552368,
  "tpm_overlap_gm": 0.47385039925575256,
  "tpm_overlap_wm": 0.4991395175457001,
  "wm2max": 0.6602342851461136
}